drb/drivers/wxs/__init__.py
drb/drivers/wxs/_version.py
drb/drivers/wxs/wXs_node.py
drb/exceptions/wxs.py
drb_driver_wxs-1.3.0.dist-info/LICENCE.txt
drb_driver_wxs-1.3.0.dist-info/METADATA
drb_driver_wxs-1.3.0.dist-info/WHEEL
drb_driver_wxs-1.3.0.dist-info/top_level.txt
drb_driver_wxs-1.3.0.dist-info/RECORD
