Metadata-Version: 2.1
Name: drb-driver-wxs
Version: 1.3.0
Summary: DRB WXS OGC Service driver
Author: GAEL Systems
Author-email: drb-python@gael.fr
License: LGPLv3
Project-URL: Documentation, http://drb-python.gitlab.io/impl/wXs
Project-URL: Source, https://gitlab.com/drb-python/impl/wXs
Classifier: Programming Language :: Python :: 3.8
Classifier: Environment :: Plugins
Classifier: License :: OSI Approved :: GNU Lesser General Public License v3 (LGPLv3)
Requires-Python: >=3.8
License-File: LICENCE.txt
Requires-Dist: drb ~=2.2.0
Requires-Dist: drb-driver-http ~=1.3.1
Requires-Dist: defusedxml >=0.7.1
Requires-Dist: drb-driver-json ~=1.3.0
